video_slide_extractor/__init__.py
video_slide_extractor/cli.py
video_slide_extractor/core.py
video_slide_extractor/output_path_format.py
video_slide_extractor-0.1.0.dist-info/entry_points.txt
video_slide_extractor-0.1.0.dist-info/WHEEL
video_slide_extractor-0.1.0.dist-info/METADATA
video_slide_extractor-0.1.0.dist-info/RECORD
