Metadata-Version: 2.1
Name: video-slide-extractor
Version: 0.1.0
Summary: 
Author: Tim Vergenz
Author-email: vergenzt@gmail.com
Requires-Python: >=3.10,<4.0
Classifier: Programming Language :: Python :: 3
Classifier: Programming Language :: Python :: 3.10
Provides-Extra: debug
Requires-Dist: docopt (>=0.6.2,<0.7.0)
Requires-Dist: ipdb (>=0.13.9,<0.14.0); extra == "debug"
Requires-Dist: more-itertools (>=8.12.0,<9.0.0)
Requires-Dist: opencv-python (>=4.5.5,<5.0.0)
Requires-Dist: single-source (>=0.3.0,<0.4.0)
Requires-Dist: tqdm (>=4.63.0,<5.0.0)
